togura/__init__.py
togura/__main__.py
togura/cli.py
togura/config.py
togura/html.py
togura/importer.py
togura/jalc.py
togura/jpcoar.py
togura/migrate.py
togura/resourcesync.py
togura/ro_crate.py
togura/togura.py
togura/.vscode/extensions.json
togura/.vscode/settings.json
togura/samples/00_sample/article.pdf
togura/samples/00_sample/dataset.txt
togura/samples/00_sample/jpcoar20.yaml
togura/samples/01_departmental_bulletin_paper_oa/jpcoar20.yaml
togura/samples/02_journal_article_embargoed/jpcoar20.yaml
togura/samples/03_journal_article_oa/jpcoar20.yaml
togura/samples/04_journal_article_accepted_embargoed/jpcoar20.yaml
togura/samples/05_doctoral_thesis_oa/jpcoar20.yaml
togura/samples/06_doctoral_thesis_published/jpcoar20.yaml
togura/samples/07_dataset/jpcoar20.yaml
togura/samples/08_conference_object/jpcoar20.yaml
togura/samples/09_departmental_bulletin_paper_restricted_access/jpcoar20.yaml
togura/samples/10_journal_article_metadata_only_external_link/jpcoar20.yaml
togura/samples/11_dataset_external_link/jpcoar20.yaml
togura/samples/12_digital_archive/jpcoar20.yaml
togura/samples/13_digital_archive_dataset_series/jpcoar20.yaml
togura/schema/jpcoar.json
togura/schema/jpcoar.yaml
togura/templates/bootstrap.html
togura/templates/footer.j2
togura/templates/index.j2
togura/templates/index_page.j2
togura/templates/show.j2
togura/templates/style.css
togura/templates/images/logo.png
togura/templates/images/logo.svg
togura-0.1.0a10.dist-info/licenses/LICENSE
togura-0.1.0a10.dist-info/METADATA
togura-0.1.0a10.dist-info/WHEEL
togura-0.1.0a10.dist-info/entry_points.txt
togura-0.1.0a10.dist-info/top_level.txt
togura-0.1.0a10.dist-info/RECORD
