Metadata-Version: 2.4
Name: togura
Version: 0.1.0a10
Summary: 極めてシンプルな機関リポジトリ
Author-email: Kosuke Tanabe <nabeta@fastmail.fm>
License-Expression: CC0-1.0
Project-URL: Homepage, https://github.com/nabeta/togura
Project-URL: Issues, https://github.com/nabeta/togura/issues
Requires-Python: >=3.11
License-File: LICENSE
Requires-Dist: habanero>=2.3.0
Requires-Dist: more-itertools>=10.8.0
Requires-Dist: oaipmh-scythe>=0.13.0
Requires-Dist: openpyxl>=3.1.5
Requires-Dist: pandas>=2.3.3
Requires-Dist: pyalex>=0.18
Requires-Dist: pytest>=8.4.2
Requires-Dist: pytest-cov>=7.0.0
Requires-Dist: python-iso639>=2025.2.18
Requires-Dist: resync>=2.0.1
Requires-Dist: rocrate>=0.14.0
Requires-Dist: ruamel-yaml>=0.18.15
Requires-Dist: setuptools>=80.9.0
Requires-Dist: typer>=0.17.4
Requires-Dist: xmlschema>=4.1.0
Dynamic: license-file
